odoo/addons/hr_holidays_leave_overlap/README.rst
odoo/addons/hr_holidays_leave_overlap/__init__.py
odoo/addons/hr_holidays_leave_overlap/__manifest__.py
odoo/addons/hr_holidays_leave_overlap/i18n/hr.po
odoo/addons/hr_holidays_leave_overlap/i18n/hr_holidays_leave_overlap.pot
odoo/addons/hr_holidays_leave_overlap/models/__init__.py
odoo/addons/hr_holidays_leave_overlap/models/hr_holidays.py
odoo/addons/hr_holidays_leave_overlap/static/description/icon.png
odoo/addons/hr_holidays_leave_overlap/tests/__init__.py
odoo/addons/hr_holidays_leave_overlap/tests/test_leave_overlap.py
odoo11_addon_hr_holidays_leave_overlap-11.0.1.0.0.99.dev4.dist-info/METADATA
odoo11_addon_hr_holidays_leave_overlap-11.0.1.0.0.99.dev4.dist-info/WHEEL
odoo11_addon_hr_holidays_leave_overlap-11.0.1.0.0.99.dev4.dist-info/top_level.txt
odoo11_addon_hr_holidays_leave_overlap-11.0.1.0.0.99.dev4.dist-info/RECORD
